{
	"allVersions": false,
	"autoNames": true,
	"customGameDir": "",
	"customGameDirForVersions": true,
	"DEBUG_MODE": true,
	"downloadVersions": false,
	"hidePlayerSafetyDisclaimer": true,
	"javaArgs": "",
	"minecraftFolder": {
		"Darwin": "~/Library/Application Support/minecraft",
		"Linux": "~/.minecraft",
		"Windows": "%APPDATA%/.minecraft"
	},
	"moddedVersions": true,
	"notPlayedVersions": true,
	"officialVersions": true,
	"old_alpha": true,
	"old_beta": true,
	"pendingVersions": true,
	"playedVersions": true,
	"releases": true,
	"resolutionHeight": 0,
	"resolutionWidth": 0,
	"snapshots": true,
	"sortBy": "releaseTime",
	"specialVersions": {
		"rd-131655": "Cave game tech test 131655",
		"c0.0.11a": "c0.0.12a-dev",
		"c0.0.13a": "c0.0.13a-dev",
		"c0.0.15a-1": "c0.0.15a Multiplayer Test 1",
		"c0.0.15a-2": "c0.0.15a Multiplayer Test 2",
		"c0.0.15a-3": "c0.0.15a Multiplayer Test 3",
		"c0.0.15a-4": "c0.0.15a Multiplayer Test 4",
		"c0.0.15a-5": "c0.0.15a Multiplayer Test 5",
		"c0.0.15a-6": "c0.0.15a Multiplayer Test 6",
		"c0.0.15a-7": "c0.0.15a Multiplayer Test 7",
		"c0.0.15a-8": "c0.0.15a Multiplayer Test 8",
		"c0.24_st": "c0.24 Survival Test",
		"c0.24_st_01": "c0.24 Survival Test 1",
		"c0.24_st_02": "c0.24 Survival Test 2",
		"c0.24_st_03": "c0.24 Survival Test 3",
		"c0.25_st": "c0.25 Survival Test",
		"c0.25_st_01": "c0.25 Survival Test 1",
		"c0.25_st_02": "c0.25 Survival Test 2",
		"c0.25_st_03": "c0.25 Survival Test 3",
		"c0.25_st_04": "c0.25 Survival Test 4",
		"c0.25_05_st": "c0.25 Survival Test 5",
		"c0.26_st": "c0.26 Survival Test",
		"c0.27_st": "c0.27 Survival Test",
		"in-20100113 Creative": "in-20100113 Creative",
		"inf-20100618": "inf-20100618 (Seecret Friday 1)",
		"inf-20100625-2": "inf-20100625-2 (Seecret Friday 2)",
		"inf-20100630-2": "a1.0.0",
		"a1.0.1": "a1.0.1 (Seecret Friday 3)",
		"a1.0.4": "a1.0.4 (Seecret Friday 4)",
		"a1.0.6": "a1.0.6 (Seecret Friday 5)",
		"a1.0.11": "a1.0.11 (Seecret Friday 6)",
		"a1.0.13_01-2": "a1.0.13_01 (1K IN 24h)",
		"a1.0.14": "a1.0.14 (Seecret Friday 7)",
		"a1.0.15": "a1.0.15 (First SMP version)",
		"a1.0.17": "a1.0.17 (Seecret Friday 8)",
		"a1.1.0": "a1.1.0 (Seecret Friday 9)",
		"a1.1.1": "a1.1.1 (Seecret Saturday 1)",
		"a1.2.0": "a1.2.0 (Halloween Update)",
		"b1.4.0": "b1.4.0 (Locked chests)",
		"2point0_red": "2.0 Red",
		"2point0_purple": "2.0 Purple",
		"2point0_blue": "2.0 Blue",
		"15w14a": "15w14a The Love and Hugs Update",
		"1.RV-Pre1": "1.RV Pre-Release 1 (Trendy Update)",
		"3D Shareware v1.34": "3D Shareware v1.34",
		"20w14infinite": "20w14∞ (Ultimate Content)",
		"1.14_combat-212796": "1.14.3 - Combat Test",
		"1.14_combat-0": "Combat Test 2",
		"1.14_combat-1": "Combat Test 2b",
		"1.14_combat-2": "Combat Test 2c",
		"1.14_combat-3": "Combat Test 3",
		"1.15_combat-0": "Combat Test 3b",
		"1.15_combat-1": "Combat Test 4",
		"1.15_combat-2": "Combat Test 4b",
		"1.15_combat-3": "Combat Test 4c",
		"1.15_combat-4": "Combat Test 4d",
		"1.15_combat-5": "Combat Test 4e",
		"1.15_combat-6": "Combat Test 5",
		"1.16_combat-0": "Combat Test 6",
		"1.16_combat-1": "Combat Test 7",
		"1.16_combat-2": "Combat Test 7b",
		"1.16_combat-3": "Combat Test 7c",
		"1.16_combat-4": "Combat Test 8",
		"1.16_combat-5": "Combat Test 8b",
		"1.16_combat-6": "Combat Test 8c",
		"1.18_experimental-snapshot-1": "1.18 Experimental snapshot 1",
		"1.18_experimental-snapshot-2": "1.18 Experimental snapshot 2",
		"1.18_experimental-snapshot-3": "1.18 Experimental snapshot 3",
		"1.18_experimental-snapshot-4": "1.18 Experimental snapshot 4",
		"1.18_experimental-snapshot-5": "1.18 Experimental snapshot 5",
		"1.18_experimental-snapshot-6": "1.18 Experimental snapshot 6",
		"1.18_experimental-snapshot-7": "1.18 Experimental snapshot 7"
	},
	"stringReplace": {
		"a1": "Alpha 1",
		"b1": "Beta 1",
		"Beta 1.9": "Snapshot 1.0",
		"c0.": "Classic 0.",
		"in-": "Indev ",
		"inf-": "Infdev ",
		"mc-": "Pre-Classic ",
		"-pre": " Pre-Release ",
		"-rc": " Release Candidate ",
		"rd-": "Pre-Classic ",
		"-tb": " Test Build "
	},
	"typeNames": {
		"release": "Release",
		"snapshot": "Snapshot",
		"pending": "Pending"
	}
}